<?xml version="1.0" encoding="UTF-8"?>
<objects serializationModel="Studio.02.02.00">
	<object class="AudioFile" id="{9a12a9b3-2ef1-48ae-9f8a-7a7c49e2a09c}">
		<property name="assetPath">
			<value>SFX/SFX_-_transmission_02.ogg</value>
		</property>
		<property name="frequencyInKHz">
			<value>44.0999985</value>
		</property>
		<property name="channelCount">
			<value>2</value>
		</property>
		<property name="length">
			<value>2.0889795918367349</value>
		</property>
		<relationship name="masterAssetFolder">
			<destination>{43bb3bb6-a8ea-4d69-ae36-71108df2e3a5}</destination>
		</relationship>
	</object>
</objects>
