<?xml version="1.0" encoding="UTF-8"?>
<objects serializationModel="Studio.02.02.00">
	<object class="AudioFile" id="{b0a8fb2a-9884-4b1d-964f-f970c7ee006e}">
		<property name="assetPath">
			<value>alarm 1.wav</value>
		</property>
		<property name="frequencyInKHz">
			<value>48</value>
		</property>
		<property name="channelCount">
			<value>2</value>
		</property>
		<property name="length">
			<value>34.666687500000002</value>
		</property>
		<relationship name="masterAssetFolder">
			<destination>{43bb3bb6-a8ea-4d69-ae36-71108df2e3a5}</destination>
		</relationship>
	</object>
</objects>
